scene_forge/__init__.py
scene_forge/_version.py
scene_forge/subpackage_template/__init__.py
scene_forge/subpackage_template/module_template.py
scene_forge/subpackage_template/tests/__init__.py
scene_forge/subpackage_template/tests/test_class_template.py
scene_forge-0.0.0.dist-info/LICENSE
scene_forge-0.0.0.dist-info/METADATA
scene_forge-0.0.0.dist-info/WHEEL
scene_forge-0.0.0.dist-info/top_level.txt
scene_forge-0.0.0.dist-info/RECORD
