Metadata-Version: 2.1
Name: scene-forge
Version: 0.0.0
Summary: Python package to generate scenes using radiative transfer modelling. This package wraps external radiative transfer codes, and uses these to make simulated scenes for Earth Observation measurements.
Home-page: https://gitlab.npl.co.uk/eco/tools/scene_forge
Author: Pieter De Vis
Author-email: pieter.de.vis@npl.co.uk
License: None
Classifier: Development Status :: 2 - Pre-Alpha
Classifier: Programming Language :: Python
Classifier: Programming Language :: Python :: 3.6
Classifier: Programming Language :: Python :: 3.7
Classifier: Programming Language :: Python :: 3.8
License-File: LICENSE
Provides-Extra: dev
Requires-Dist: pre-commit ; extra == 'dev'
Requires-Dist: tox ; extra == 'dev'
Requires-Dist: sphinx ; extra == 'dev'
Requires-Dist: sphinx-book-theme ; extra == 'dev'
Requires-Dist: sphinx-design ; extra == 'dev'
Requires-Dist: ipython ; extra == 'dev'
